nonebot_plugin_session_orm/__init__.py
nonebot_plugin_session_orm/migrations/2e0c173949d3_constraint_name.py
nonebot_plugin_session_orm/migrations/71a72119935f_data_migrate.py
nonebot_plugin_session_orm/migrations/fff55366306e_init_db.py
nonebot_plugin_session_orm/model.py
nonebot_plugin_session_orm/py.typed
nonebot_plugin_session_orm-0.2.2.dist-info/LICENSE
nonebot_plugin_session_orm-0.2.2.dist-info/METADATA
nonebot_plugin_session_orm-0.2.2.dist-info/WHEEL
nonebot_plugin_session_orm-0.2.2.dist-info/RECORD
