Metadata-Version: 2.3
Name: nonebot_plugin_session_orm
Version: 0.2.2
Summary: session 插件 orm 扩展
Home-page: https://github.com/noneplugin/nonebot-plugin-session-orm
License: MIT
Author: meetwq
Author-email: meetwq@gmail.com
Requires-Python: >=3.9,<4.0
Classifier: License :: OSI Approved :: MIT License
Classifier: Programming Language :: Python :: 3
Classifier: Programming Language :: Python :: 3.9
Classifier: Programming Language :: Python :: 3.10
Classifier: Programming Language :: Python :: 3.11
Classifier: Programming Language :: Python :: 3.12
Classifier: Programming Language :: Python :: 3.13
Requires-Dist: nonebot-plugin-orm (>=0.7.0,<1.0.0)
Requires-Dist: nonebot-plugin-session (>=0.3.0,<0.4.0)
Requires-Dist: nonebot2 (>=2.3.0,<3.0.0)
Project-URL: Repository, https://github.com/noneplugin/nonebot-plugin-session-orm
